LICENSE
MANIFEST.in
README.md
setup.py
django_pipeline_compass_compiler.egg-info/PKG-INFO
django_pipeline_compass_compiler.egg-info/SOURCES.txt
django_pipeline_compass_compiler.egg-info/dependency_links.txt
django_pipeline_compass_compiler.egg-info/not-zip-safe
django_pipeline_compass_compiler.egg-info/top_level.txt
pipeline_compiler/__init__.py
pipeline_compiler/compass.py