Metadata-Version: 1.1
Name: django-pipeline-compass-compiler
Version: 0.1.2
Summary: 
